swh/indexer/__init__.py
swh/indexer/bibtex.py
swh/indexer/cli.py
swh/indexer/codemeta.py
swh/indexer/fossology_license.py
swh/indexer/indexer.py
swh/indexer/metadata.py
swh/indexer/metadata_detector.py
swh/indexer/mimetype.py
swh/indexer/namespaces.py
swh/indexer/origin_head.py
swh/indexer/py.typed
swh/indexer/rehash.py
swh/indexer/data/Gitea.csv
swh/indexer/data/composer.csv
swh/indexer/data/nuget.csv
swh/indexer/data/pubspec.csv
swh/indexer/data/codemeta/CITATION
swh/indexer/data/codemeta/LICENSE
swh/indexer/data/codemeta/codemeta-2.0.jsonld
swh/indexer/data/codemeta/codemeta-3.0.jsonld
swh/indexer/data/codemeta/crosswalk.csv
swh/indexer/data/schema.org/CITATION
swh/indexer/data/schema.org/LICENSE
swh/indexer/data/schema.org/schemaorgcontext.jsonld
swh/indexer/metadata_dictionary/__init__.py
swh/indexer/metadata_dictionary/base.py
swh/indexer/metadata_dictionary/cff.py
swh/indexer/metadata_dictionary/codemeta.py
swh/indexer/metadata_dictionary/composer.py
swh/indexer/metadata_dictionary/dart.py
swh/indexer/metadata_dictionary/gitea.py
swh/indexer/metadata_dictionary/github.py
swh/indexer/metadata_dictionary/maven.py
swh/indexer/metadata_dictionary/npm.py
swh/indexer/metadata_dictionary/nuget.py
swh/indexer/metadata_dictionary/python.py
swh/indexer/metadata_dictionary/ruby.py
swh/indexer/metadata_dictionary/utils.py
swh/indexer/storage/__init__.py
swh/indexer/storage/converters.py
swh/indexer/storage/db.py
swh/indexer/storage/exc.py
swh/indexer/storage/in_memory.py
swh/indexer/storage/interface.py
swh/indexer/storage/metrics.py
swh/indexer/storage/model.py
swh/indexer/storage/writer.py
swh/indexer/storage/api/__init__.py
swh/indexer/storage/api/client.py
swh/indexer/storage/api/serializers.py
swh/indexer/storage/api/server.py
swh/indexer/storage/sql/10-superuser-init.sql
swh/indexer/storage/sql/20-enums.sql
swh/indexer/storage/sql/30-schema.sql
swh/indexer/storage/sql/50-data.sql
swh/indexer/storage/sql/50-func.sql
swh/indexer/storage/sql/60-indexes.sql
swh_indexer-4.3.1.dist-info/licenses/AUTHORS
swh_indexer-4.3.1.dist-info/licenses/LICENSE
swh_indexer-4.3.1.dist-info/METADATA
swh_indexer-4.3.1.dist-info/WHEEL
swh_indexer-4.3.1.dist-info/entry_points.txt
swh_indexer-4.3.1.dist-info/top_level.txt
swh_indexer-4.3.1.dist-info/RECORD
