Metadata-Version: 2.4
Name: swh.indexer
Version: 4.3.1
Summary: Software Heritage indexer
Author-email: Software Heritage developers <swh-devel@inria.fr>
Project-URL: Homepage, https://gitlab.softwareheritage.org/swh/devel/swh-indexer
Project-URL: Bug Reports, https://gitlab.softwareheritage.org/swh/devel/swh-indexer/-/issues
Project-URL: Funding, https://www.softwareheritage.org/donate
Project-URL: Documentation, https://docs.softwareheritage.org/devel/swh-indexer/
Project-URL: Source, https://gitlab.softwareheritage.org/swh/devel/swh-indexer.git
Classifier: Programming Language :: Python :: 3
Classifier: Intended Audience :: Developers
Classifier: License :: OSI Approved :: GNU General Public License v3 (GPLv3)
Classifier: Operating System :: OS Independent
Classifier: Development Status :: 5 - Production/Stable
Requires-Python: >=3.9
License-File: LICENSE
License-File: AUTHORS
Requires-Dist: python-magic>=0.4.13
Requires-Dist: click
Requires-Dist: frozendict!=2.1.2
Requires-Dist: iso8601
Requires-Dist: pybtex>=0.25.0
Requires-Dist: pyld
Requires-Dist: rdflib>=7.1.4
Requires-Dist: sentry-sdk
Requires-Dist: typing-extensions
Requires-Dist: xmltodict
Requires-Dist: swh.core[db,http]>=4.0.0
Requires-Dist: swh.model>=8.4.0
Requires-Dist: swh.objstorage>=2.3.1
Requires-Dist: swh.storage>=3.0.0
Requires-Dist: swh.journal>=0.1.0
Provides-Extra: testing
Requires-Dist: confluent-kafka; extra == "testing"
Requires-Dist: hypothesis>=3.11.0; extra == "testing"
Requires-Dist: pytest>=8.1; extra == "testing"
Requires-Dist: pytest-mock; extra == "testing"
Requires-Dist: swh.core[testing]>=3.0.0; extra == "testing"
Requires-Dist: swh.journal[pytest]>=2.0.0; extra == "testing"
Requires-Dist: swh.storage[pytest]>=3.1.0; extra == "testing"
Requires-Dist: types-confluent-kafka; extra == "testing"
Requires-Dist: types-pyyaml; extra == "testing"
Requires-Dist: types-xmltodict; extra == "testing"
Dynamic: license-file
